fastbase64-0.1.0.dist-info/METADATA
fastbase64-0.1.0.dist-info/WHEEL
fastbase64-0.1.0.dist-info/licenses/LICENSE
fastbase64/__init__.py
fastbase64/__init__.pyi
fastbase64/py.typed
fastbase64/fastbase64.cpython-313-s390x-linux-gnu.so
fastbase64-0.1.0.dist-info/RECORD
